MANIFEST.in
README.txt
setup.py
o2w/__init__.py
o2w/templates/__init__.py
o2w/templates/templates/404.html
o2w/templates/templates/500.html
o2w/templates/templates/html5.html
o2w/templates/templates/sitemap.xml
o2w_templates.egg-info/PKG-INFO
o2w_templates.egg-info/SOURCES.txt
o2w_templates.egg-info/dependency_links.txt
o2w_templates.egg-info/top_level.txt