Metadata-Version: 1.0
Name: o2w-templates
Version: 0.0.1
Summary: Default sane templates 500, 404, html5, sitemap.xml
Home-page: http://www.o2w.es/
Author: José Sánchez Moreno
Author-email: jose@o2w.es
License: LICENSE.txt
Platform: UNKNOWN
